{
    "AX": {
        "error": 0.0,
        "fit": "default",
        "references": [],
        "value": 1.0
    },
    "CDD": {
        "error": 0.0026266832720458046,
        "fit": "Average",
        "reference_data": {
            "es": [
                0.0009785507885859636,
                0.0009295646660589001,
                0.0009470035354450109,
                0.001005146301865557,
                0.0008831446034118461
            ],
            "vs": [
                0.9583917148441944,
                0.9594258234667182,
                0.9640629330379922,
                0.9632388693416906,
                0.9589787992630883
            ],
            "xs": [
                1678632119.0,
                1678642601.0,
                1678653099.0,
                1678663585.0,
                1678667055.0
            ]
        },
        "reference_detector": "H1",
        "references": [
            {
                "exclude": "ok",
                "record_id": "a-01-A-7631",
                "uuid": "2cfd4af8-b5c6-452e-b8b0-69f695aa53a7"
            },
            {
                "exclude": "ok",
                "record_id": "a-01-A-7632",
                "uuid": "a7325b84-5771-40af-b272-cc4bdb9485c5"
            },
            {
                "exclude": "ok",
                "record_id": "a-01-A-7633",
                "uuid": "9b528c23-f640-460e-8d26-4ea0e2296fdb"
            },
            {
                "exclude": "ok",
                "record_id": "a-01-A-7634",
                "uuid": "fd917ef4-15fb-4713-989e-338f1e11ba6f"
            },
            {
                "exclude": "ok",
                "record_id": "a-01-A-7635",
                "uuid": "1a56587f-c2a9-4a66-8764-5143ac8c29a2"
            }
        ],
        "reviewed": true,
        "standard_ratio": 295.5,
        "value": 0.9608196279907368
    },
    "H1": {
        "error": 0.0,
        "fit": "default",
        "references": [],
        "value": 1.0
    },
    "L1": {
        "error": 0.0,
        "fit": "default",
        "references": [],
        "value": 1.0
    },
    "L2": {
        "error": 0.0,
        "fit": "default",
        "references": [],
        "value": 1.0
    }
}