{
    "AX": {
        "error": 0.004910914365232871,
        "error_type": "SEM",
        "filter_outliers_dict": {
            "filter_outliers": true,
            "iterations": 1,
            "std_devs": 2
        },
        "fit": "Average",
        "value": 0.00284792249717534
    },
    "CDD": {
        "error": 3.758707981370808e-06,
        "error_type": "SEM",
        "filter_outliers_dict": {
            "filter_outliers": false,
            "iterations": 1,
            "std_devs": 2
        },
        "fit": "Average",
        "value": 2.5187577724598805e-06
    },
    "H1": {
        "error": 0.018023514043214832,
        "error_type": "SEM",
        "filter_outliers_dict": {
            "filter_outliers": true,
            "iterations": 1,
            "std_devs": 2
        },
        "fit": "Average",
        "value": 0.011915197726827212
    },
    "L1": {
        "error": 0.006751992663662204,
        "error_type": "SEM",
        "filter_outliers_dict": {
            "filter_outliers": true,
            "iterations": 1,
            "std_devs": 2
        },
        "fit": "Average",
        "value": 0.018194562674675094
    },
    "L2": {
        "error": 0.007440229449342574,
        "error_type": "SEM",
        "filter_outliers_dict": {
            "filter_outliers": false,
            "iterations": 1,
            "std_devs": 2
        },
        "fit": "Average",
        "value": -0.003181082025867884
    }
}